Workbook

Sheet Index
A1: FOREX DSS - Data Visualisation Workbook
A2: Enterprise Computing Phase 2 | Sashank Vuppala | SV4SV Industries
A4: Stakeholder dashboards
A6: =HYPERLINK("#Trader_Dashboard!A1","Trader Dashboard") -> Trader Dashboard | B6: Take-or-reject signal, confidence, risk parameters, recent performance
A7: =HYPERLINK("#Coach_Dashboard!A1","Coach Dashboard") -> Coach Dashboard | B7: Eight-filter evaluation table and setup-quality relationship
A8: =HYPERLINK("#Institutional_Dashboard!A1","Institutional Dashboard") -> Institutional Dashboard | B8: Portfolio aggregate metrics, equity curve, per-pair breakdown
A9: =HYPERLINK("#Operational_Dashboard!A1","Operational Dashboard") -> Operational Dashboard | B9: System soundness, data completeness and error-rate monitoring
A10: =HYPERLINK("#Input!A1","Input (new bar entry)") -> Input (new bar entry) | B10: Manual data entry point that triggers evaluation
A11: =HYPERLINK("#Logic!A1","Logic (evaluation engine)") -> Logic (evaluation engine) | B11: Filter gates, displacement, confidence and risk maths
A12: =HYPERLINK("#Calculation_Breakdown!A1","Calculation Breakdown") -> Calculation Breakdown | B12: Step-by-step derivation for teaching
A13: =HYPERLINK("#Trade_History!A1","Trade History") -> Trade History | B13: Accumulated evaluation log driving the aggregates
A15: Colour convention (consistent across all dashboards)
B16: PASS / Win / Long / Operational
B17: FAIL / Loss / Short / Failed
B18: Degraded / Caution
B19: Inactive / Not applicable
A21: Data imported for the period ending 13 March 2026 (static dataset)

Sheet Trader_Dashboard
A1: Trader Dashboard
A2: Primary end user: take-or-reject in seconds. Data imported for the period ending 13 March 2026 (static dataset)
A4: =Logic!B31 -> TAKE | E4: Direction | F4: =Logic!B32 -> BUY
E5: Confidence | F5: =Logic!B17 -> 1
E6: Risk-reward | F6: =Logic!B18&":1" -> 3:1
E7: Entry | F7: =Logic!B33 -> 1.0847
E8: Stop loss | F8: =Logic!B37 -> 1.0783549
E9: Take profit | F9: =Logic!B38 -> 1.0955386
A11: Recent signals
A12: Date | B12: Pair | C12: Dir | D12: Conf | E12: RR | F12: Outcome | G12: P&L (pips)
A13: =Trade_History!B29 -> 2026-04-15 | B13: =Trade_History!C29 -> GBP/USD | C13: =Trade_History!D29 -> SELL | D13: =Trade_History!I29 -> 0.82 | E13: =Trade_History!H29&":1" -> 2:1 | F13: =Trade_History!K29 -> Win | G13: =Trade_History!L29 -> 44.2
A14: =Trade_History!B30 -> 2026-04-16 | B14: =Trade_History!C30 -> USD/JPY | C14: =Trade_History!D30 -> SELL | D14: =Trade_History!I30 -> 0.9 | E14: =Trade_History!H30&":1" -> 3:1 | F14: =Trade_History!K30 -> Loss | G14: =Trade_History!L30 -> -18.9
A15: =Trade_History!B31 -> 2026-04-17 | B15: =Trade_History!C31 -> EUR/USD | C15: =Trade_History!D31 -> BUY | D15: =Trade_History!I31 -> 0.79 | E15: =Trade_History!H31&":1" -> 2:1 | F15: =Trade_History!K31 -> Win | G15: =Trade_History!L31 -> 46
A16: =Trade_History!B32 -> 2026-04-18 | B16: =Trade_History!C32 -> EUR/USD | C16: =Trade_History!D32 -> BUY | D16: =Trade_History!I32 -> 0.78 | E16: =Trade_History!H32&":1" -> 2:1 | F16: =Trade_History!K32 -> Loss | G16: =Trade_History!L32 -> -18
A17: =Trade_History!B33 -> 2026-04-19 | B17: =Trade_History!C33 -> GBP/USD | C17: =Trade_History!D33 -> BUY | D17: =Trade_History!I33 -> 0.58 | E17: =Trade_History!H33&":1" -> 2:1 | F17: =Trade_History!K33 -> Win | G17: =Trade_History!L33 -> 37.8
A18: =Trade_History!B34 -> 2026-04-21 | B18: =Trade_History!C34 -> USD/JPY | C18: =Trade_History!D34 -> BUY | D18: =Trade_History!I34 -> 0.45 | E18: =Trade_History!H34&":1" -> 1:1 | F18: =Trade_History!K34 -> Win | G18: =Trade_History!L34 -> 17.7
A19: =Trade_History!B35 -> 2026-04-22 | B19: =Trade_History!C35 -> GBP/USD | C19: =Trade_History!D35 -> BUY | D19: =Trade_History!I35 -> 0.94 | E19: =Trade_History!H35&":1" -> 3:1 | F19: =Trade_History!K35 -> Win | G19: =Trade_History!L35 -> 56.1
A20: =Trade_History!B36 -> 2026-04-24 | B20: =Trade_History!C36 -> EUR/USD | C20: =Trade_History!D36 -> SELL | D20: =Trade_History!I36 -> 0.34 | E20: =Trade_History!H36&":1" -> 1:1 | F20: =Trade_History!K36 -> Loss | G20: =Trade_History!L36 -> -24.8
A21: =Trade_History!B37 -> 2026-04-26 | B21: =Trade_History!C37 -> GBP/USD | C21: =Trade_History!D37 -> BUY | D21: =Trade_History!I37 -> 0.9 | E21: =Trade_History!H37&":1" -> 3:1 | F21: =Trade_History!K37 -> Win | G21: =Trade_History!L37 -> 74.1
A22: =Trade_History!B38 -> 2026-04-28 | B22: =Trade_History!C38 -> EUR/USD | C22: =Trade_History!D38 -> SELL | D22: =Trade_History!I38 -> 0.82 | E22: =Trade_History!H38&":1" -> 2:1 | F22: =Trade_History!K38 -> Win | G22: =Trade_History!L38 -> 33.4

Sheet Coach_Dashboard
A1: Coach Dashboard
A2: Educational stakeholder: trace pass/fail logic filter by filter. Data imported for the period ending 13 March 2026 (static dataset)
A4: Current bar - eight-filter evaluation
A5: Filter | B5: Condition | C5: Tested value | D5: Result | E5: Plain-language explanation
A6: E1 | B6: Recent range / prior range >= 1.0 | C6: =Logic!C21 -> 3.2945736 | D6: =Logic!D21 -> PASS | E6: Confirms the market is expanding, not ranging, where structure breaks fail more often.
A7: E2 | B7: 0.02% <= ATR/price <= 0.35% | C7: =Logic!C22 -> 0.0016653716 | D7: =Logic!D22 -> PASS | E7: Confirms volatility is normal, neither too dead to move nor too wild to trust.
A8: E3 | B8: Efficiency >= 0.35 | C8: =Logic!C23 -> 0.68627451 | D8: =Logic!D23 -> PASS | E8: Confirms the candle is body-driven, not a wick, so momentum is genuine.
A9: E4 | B9: Close on correct side of rising/falling 21 EMA | C9: =Logic!C24 -> 1.0614792 | D9: =Logic!D24 -> PASS | E9: Confirms the trade aligns with the higher-timeframe trend, not against it.
A10: E5 | B10: Displacement >= 1.5x avg body | C10: =Logic!C25 -> 4.53284 | D10: =Logic!D25 -> PASS | E10: Confirms the displacement is strong enough to be real institutional momentum.
A11: E6 | B11: FVG gap >= 0.4x ATR | C11: =Logic!C26 -> 0.0009 | D11: =Logic!D26 -> PASS | E11: Confirms the fair value gap is large enough to be a meaningful imbalance.
A12: E7 | B12: Clean close inside zone | C12: =Logic!C27 -> 1 | D12: =Logic!D27 -> PASS | E12: Confirms price actually closed in the zone rather than only grazing it.
A13: E8 | B13: Bars since last >= 5, no lockout | C13: =Logic!C28 -> 8 | D13: =Logic!D28 -> PASS | E13: Confirms spacing from the last trade and that no two-loss lockout is active.
A14: Overall decision | D14: =Logic!B31 -> TAKE | E14: =HYPERLINK("#Calculation_Breakdown!A1","See full calculation breakdown >") -> See full calculation breakdown >
A16: Setup quality relationship: displacement ratio vs trade P&L

Sheet Institutional_Dashboard
A1: Institutional Dashboard
A2: Governance stakeholder: is the system preserving capital within risk tolerance? Data imported for the period ending 13 March 2026 (static dataset)
A4: Total return (pips) | C4: Trades | E4: Win rate | G4: Avg win (pips)
A5: =SUM(Trade_History!L2:L38) -> 493 | C5: =COUNT(Trade_History!A2:A38) -> 37 | E5: =COUNTIF(Trade_History!K2:K38,"Win")/COUNT(Trade_History!A2:A38) -> 0.56756757 | G5: =AVERAGEIF(Trade_History!K2:K38,"Win",Trade_History!L2:L38) -> 39.604762
A7: Avg loss (pips) | C7: Profit factor | E7: Max DD (pips) | G7: Avg RR tier
A8: =AVERAGEIF(Trade_History!K2:K38,"Loss",Trade_History!L2:L38) -> -21.16875 | C8: =SUMIF(Trade_History!K2:K38,"Win",Trade_History!L2:L38)/-SUMIF(Trade_History!K2:K38,"Loss",Trade_History!L2:L38) -> 2.4555654 | E8: =MAX(Trade_History!O2:O38) -> 87.7 | G8: =AVERAGE(Trade_History!H2:H38) -> 1.8648649
A10: Drawdown vs 120-pip tolerance band | C10: =IF(MAX(Trade_History!O2:O38)>120,"BREACH","WITHIN TOLERANCE") -> WITHIN TOLERANCE
A12: Performance by currency pair
A13: Pair | B13: Trades | C13: Win rate | D13: Net (pips) | E13: Avg RR
A14: EUR/USD | B14: =COUNTIF(Trade_History!C2:C38,"EUR/USD") -> 24 | C14: =IFERROR(COUNTIFS(Trade_History!C2:C38,"EUR/USD",Trade_History!K2:K38,"Win")/COUNTIF(Trade_History!C2:C38,"EUR/USD"),0) -> 0.41666667 | D14: =SUMIF(Trade_History!C2:C38,"EUR/USD",Trade_History!L2:L38) -> 108.1 | E14: =IFERROR(AVERAGEIF(Trade_History!C2:C38,"EUR/USD",Trade_History!H2:H38),0) -> 1.7916667
A15: GBP/USD | B15: =COUNTIF(Trade_History!C2:C38,"GBP/USD") -> 7 | C15: =IFERROR(COUNTIFS(Trade_History!C2:C38,"GBP/USD",Trade_History!K2:K38,"Win")/COUNTIF(Trade_History!C2:C38,"GBP/USD"),0) -> 0.85714286 | D15: =SUMIF(Trade_History!C2:C38,"GBP/USD",Trade_History!L2:L38) -> 233.6 | E15: =IFERROR(AVERAGEIF(Trade_History!C2:C38,"GBP/USD",Trade_History!H2:H38),0) -> 2
A16: USD/JPY | B16: =COUNTIF(Trade_History!C2:C38,"USD/JPY") -> 6 | C16: =IFERROR(COUNTIFS(Trade_History!C2:C38,"USD/JPY",Trade_History!K2:K38,"Win")/COUNTIF(Trade_History!C2:C38,"USD/JPY"),0) -> 0.83333333 | D16: =SUMIF(Trade_History!C2:C38,"USD/JPY",Trade_History!L2:L38) -> 151.3 | E16: =IFERROR(AVERAGEIF(Trade_History!C2:C38,"USD/JPY",Trade_History!H2:H38),0) -> 2

Sheet Operational_Dashboard
A1: Operational Dashboard
A2: Operational stakeholder: is the system sound so results can be trusted? Data imported for the period ending 13 March 2026 (static dataset)
A4: System status
A5: Component | B5: Metric | C5: Value | D5: Status
A6: Historical data feed | B6: Bars available (>=100 required) | C6: =COUNT(Historical_Data!A2:A151) -> 150 | D6: =IF(C6>=100,"OPERATIONAL",IF(C6>=60,"DEGRADED","FAILED")) -> OPERATIONAL
A7: Evaluation validation | B7: Current bar decision produced | C7: =IF(Logic!B31<>"","Yes","No") -> Yes | D7: =IF(C7="Yes","OPERATIONAL","FAILED") -> OPERATIONAL
A8: Error rate | B8: Failed evaluations / cycles | C8: =SUM(B12:B21)/SUM(C12:C21) -> 0.014184397 | D8: =IF(C8<0.02,"OPERATIONAL",IF(C8<0.05,"DEGRADED","FAILED")) -> OPERATIONAL
A9: Data freshness | B9: Days since import | C9: =15 -> 15 | D9: =IF(C9<=30,"OPERATIONAL",IF(C9<=60,"DEGRADED","FAILED")) -> OPERATIONAL
A11: Evaluation cycle log (last 10) | B11: Errors | C11: Evals
A12: Cycle 1 | B12: 0 | C12: 12
A13: Cycle 2 | B13: 0 | C13: 15
A14: Cycle 3 | B14: 1 | C14: 14
A15: Cycle 4 | B15: 0 | C15: 13
A16: Cycle 5 | B16: 0 | C16: 16
A17: Cycle 6 | B17: 0 | C17: 15
A18: Cycle 7 | B18: 0 | C18: 14
A19: Cycle 8 | B19: 1 | C19: 15
A20: Cycle 9 | B20: 0 | C20: 13
A21: Cycle 10 | B21: 0 | C21: 14

Sheet Input
A1: Input - New Bar Entry
A2: Enter a new bar; formulas evaluate it against the stored historical dataset (manual trigger cycle).
A4: Field | B4: Value
A5: Currency pair | B5: EUR/USD
A6: Date | B6: 2026-03-13
A7: Time | B7: 08:00
A8: Open | B8: 1.0812
A9: High | B9: 1.0856
A10: Low | B10: 1.0805
A11: Close | B11: 1.0847
A12: Prior swing high | B12: 1.083
A13: Prior swing low | B13: 1.0798
A14: FVG gap size (pips) | B14: 9
A15: Retest closes cleanly? | B15: Yes
A16: Setup direction | B16: BUY
A17: Bars since last trade | B17: 8
A19: Blue cells are the only manually entered values. Every downstream figure is formula-derived.

Sheet Logic
A1: Logic - Evaluation Engine
A2: Eight Module E filter gates, displacement-to-confidence mapping and risk parameters for the current bar.
A4: CURRENT BAR METRICS
A5: Pip size | B5: =IF(Input!B5="USD/JPY",0.01,0.0001) -> 0.0001
A6: Body | B6: =ABS(Input!B11-Input!B8) -> 0.0035
A7: Range | B7: =Input!B9-Input!B10 -> 0.0051
A8: Efficiency | B8: =IF(B7=0,0,B6/B7) -> 0.68627451
A9: AvgBody14 (baseline) | B9: =Historical_Data!O151 -> 0.00077214286
A10: ATR14 (baseline) | B10: =Historical_Data!M151 -> 0.0018064286
A11: EMA21 previous | B11: =Historical_Data!N151 -> 1.0591571
A12: EMA21 prior-2 | B12: =Historical_Data!N150 -> 1.0593998
A13: EMA21 current | B13: =Input!B11*0.0909090909090909+B11*(1-0.0909090909090909) -> 1.0614792
A14: PriorRange5 (baseline) | B14: =Historical_Data!Q151 -> 0.001548
A15: ATR/price ratio | B15: =B10/Input!B11 -> 0.0016653716
A16: Displacement ratio | B16: =IF(B9=0,0,B6/B9) -> 4.53284
A17: Confidence score | B17: =MIN(1,MAX(0,(B16-1)/2)) -> 1
A18: Risk-reward tier (n:1) | B18: =IF(B17>=0.85,3,IF(B17>=0.5,2,1)) -> 3
A19: EIGHT MODULE E FILTER GATES
A20: Filter | B20: Condition | C20: Tested value | D20: Result
A21: E1 | B21: Market regime expanding (recent range >= prior range) | C21: =B7/B14 -> 3.2945736 | D21: =IF(C21>=1,"PASS","FAIL") -> PASS
A22: E2 | B22: Volatility band: ATR/price within 0.02%-0.35% | C22: =B15 -> 0.0016653716 | D22: =IF(AND(C22>=0.0002,C22<=0.0035),"PASS","FAIL") -> PASS
A23: E3 | B23: Retest candle efficiency >= 35% | C23: =B8 -> 0.68627451 | D23: =IF(C23>=0.35,"PASS","FAIL") -> PASS
A24: E4 | B24: HTF trend alignment with 21 EMA and matching slope | C24: =B13 -> 1.0614792 | D24: =IF(Input!B16="BUY",IF(AND(Input!B11>=B13,B13>B12),"PASS","FAIL"),IF(AND(Input!B11<=B13,B13<B12),"PASS","FAIL")) -> PASS
A25: E5 | B25: Displacement ratio >= 1.5x average body | C25: =B16 -> 4.53284 | D25: =IF(C25>=1.5,"PASS","FAIL") -> PASS
A26: E6 | B26: FVG gap >= 0.4x ATR | C26: =Input!B14*B5 -> 0.0009 | D26: =IF(C26>=0.4*B10,"PASS","FAIL") -> PASS
A27: E7 | B27: Retest closes cleanly inside zone (not a wick graze) | C27: =IF(Input!B15="Yes",1,0) -> 1 | D27: =IF(C27=1,"PASS","FAIL") -> PASS
A28: E8 | B28: Bars since last trade >= 5 and no two-loss lockout | C28: =Input!B17 -> 8 | D28: =IF(AND(C28>=5,NOT(AND(Trade_History!K38="Loss",Trade_History!K37="Loss"))),"PASS","FAIL") -> PASS
A29: DECISION & RISK PARAMETERS
A30: Filters passed | B30: =SUMPRODUCT(--((D21="PASS")+(D22="PASS")+(D23="PASS")+(D24="PASS")+(D25="PASS")+(D26="PASS")+(D27="PASS")+(D28="PASS"))) -> 8
A31: Signal decision | B31: =IF(AND(D21="PASS",D22="PASS",D23="PASS",D24="PASS",D25="PASS",D26="PASS",D27="PASS",D28="PASS"),"TAKE","REJECT") -> TAKE
A32: Direction | B32: =Input!B16 -> BUY
A33: Entry price | B33: =Input!B11 -> 1.0847
A34: SL buffer (xATR) | B34: =IF(B17>0.8,0.8,IF(B17>=0.6,0.5,IF(B17>=0.4,0.3,0.2))) -> 0.8
A35: Raw stop | B35: =IF(Logic!B32="BUY",MIN(Input!B13,B33)-B34*B10,MAX(Input!B12,B33)+B34*B10) -> 1.0783549
A36: Risk distance (>=2xATR) | B36: =MAX(ABS(B33-B35),2*B10) -> 0.0063451429
A37: Stop loss | B37: =IF(B32="BUY",B33-B36,B33+B36) -> 1.0783549
A38: Take profit | B38: =IF(B32="BUY",B33+MIN(B18*B36,6*B10),B33-MIN(B18*B36,6*B10)) -> 1.0955386

Sheet Calculation_Breakdown
A1: Calculation Breakdown
A2: Step-by-step derivation a coach can show a student: how the numbers become a decision.
A4: Step | B4: Formula logic | C4: Live value
A5: 1. Candle body | B5: ABS(Close - Open) | C5: =Logic!B6 -> 0.0035
A6: 2. 14-bar average body | B6: AVERAGE of last 14 historical bodies | C6: =Logic!B9 -> 0.00077214286
A7: 3. Displacement ratio | B7: Body / AvgBody14 | C7: =Logic!B16 -> 4.53284
A8: 4. Confidence score | B8: (Displacement - 1) / 2, clamped 0 to 1 | C8: =Logic!B17 -> 1
A9: 5. Risk-reward tier | B9: conf>=0.85 -> 3:1; >=0.5 -> 2:1; else 1:1 | C9: =Logic!B18&":1" -> 3:1
A10: 6. Stop-loss buffer | B10: xATR scaled by confidence band | C10: =Logic!B34 -> 0.8
A11: 7. Risk distance | B11: MAX(entry-stop, 2 x ATR) | C11: =Logic!B36 -> 0.0063451429
A12: 8. Take profit | B12: Entry +/- tier x risk, capped at 6 x ATR | C12: =Logic!B38 -> 1.0955386
A14: Filter gate logic (native Excel formula conditions)
A15: E1 PASS when RecentRange5 / PriorRange5 >= 1.0 (market regime is expanding)
A16: E2 PASS when ATR / price is between 0.0002 and 0.0035 (volatility band)
A17: E3 PASS when body / range efficiency >= 0.35
A18: E4 PASS when the close sits on the correct side of a sloping 21 EMA
A19: E5 PASS when displacement ratio >= 1.5x the average body
A20: E6 PASS when the fair value gap >= 0.4x ATR
A21: E7 PASS when the retest closes cleanly inside the zone
A22: E8 PASS when bars since last trade >= 5 and no two-loss lockout is active

Sheet Trade_History
A1: # | B1: Date | C1: Pair | D1: Direction | E1: Entry | F1: SL | G1: TP | H1: RR Tier | I1: Confidence | J1: Disp Ratio | K1: Outcome | L1: P&L (pips) | M1: Cumulative | N1: Peak | O1: Drawdown
A2: 1 | B2: 2026-03-03 | C2: EUR/USD | D2: SELL | E2: 1.08598 | F2: 1.08795 | G2: 1.08204 | H2: 2 | I2: 0.58 | J2: 2.17 | K2: Loss | L2: -19.7 | M2: =L2 -> -19.7 | N2: =MAX($M$2:M2) -> -19.7 | O2: =N2-M2 -> 0
A3: 2 | B3: 2026-03-05 | C3: EUR/USD | D3: SELL | E3: 1.07874 | F3: 1.08122 | G3: 1.07626 | H3: 1 | I3: 0.45 | J3: 1.9 | K3: Loss | L3: -24.8 | M3: =M2+L3 -> -44.5 | N3: =MAX($M$2:M3) -> -19.7 | O3: =N3-M3 -> 24.8
A4: 3 | B4: 2026-03-06 | C4: USD/JPY | D4: BUY | E4: 150.415 | F4: 150.224 | G4: 150.988 | H4: 3 | I4: 0.9 | J4: 2.8 | K4: Win | L4: 57.3 | M4: =M3+L4 -> 12.8 | N4: =MAX($M$2:M4) -> 12.8 | O4: =N4-M4 -> 0
A5: 4 | B5: 2026-03-07 | C5: EUR/USD | D5: BUY | E5: 1.07367 | F5: 1.0716 | G5: 1.07988 | H5: 3 | I5: 0.87 | J5: 2.74 | K5: Loss | L5: -20.7 | M5: =M4+L5 -> -7.9 | N5: =MAX($M$2:M5) -> 12.8 | O5: =N5-M5 -> 20.7
A6: 5 | B6: 2026-03-09 | C6: EUR/USD | D6: SELL | E6: 1.08385 | F6: 1.08565 | G6: 1.08025 | H6: 2 | I6: 0.66 | J6: 2.32 | K6: Win | L6: 36 | M6: =M5+L6 -> 28.1 | N6: =MAX($M$2:M6) -> 28.1 | O6: =N6-M6 -> 0
A7: 6 | B7: 2026-03-11 | C7: EUR/USD | D7: BUY | E7: 1.0815 | F7: 1.07908 | G7: 1.08634 | H7: 2 | I7: 0.8 | J7: 2.6 | K7: Win | L7: 48.4 | M7: =M6+L7 -> 76.5 | N7: =MAX($M$2:M7) -> 76.5 | O7: =N7-M7 -> 0
A8: 7 | B8: 2026-03-12 | C8: EUR/USD | D8: SELL | E8: 1.08462 | F8: 1.08686 | G8: 1.08238 | H8: 1 | I8: 0.44 | J8: 1.87 | K8: Win | L8: 22.4 | M8: =M7+L8 -> 98.9 | N8: =MAX($M$2:M8) -> 98.9 | O8: =N8-M8 -> 0
A9: 8 | B9: 2026-03-13 | C9: EUR/USD | D9: SELL | E9: 1.08445 | F9: 1.08668 | G9: 1.07999 | H9: 2 | I9: 0.65 | J9: 2.29 | K9: Win | L9: 44.6 | M9: =M8+L9 -> 143.5 | N9: =MAX($M$2:M9) -> 143.5 | O9: =N9-M9 -> 0
A10: 9 | B10: 2026-03-14 | C10: GBP/USD | D10: BUY | E10: 1.26972 | F10: 1.26786 | G10: 1.27158 | H10: 1 | I10: 0.48 | J10: 1.96 | K10: Win | L10: 18.6 | M10: =M9+L10 -> 162.1 | N10: =MAX($M$2:M10) -> 162.1 | O10: =N10-M10 -> 0
A11: 10 | B11: 2026-03-15 | C11: USD/JPY | D11: SELL | E11: 149.596 | F11: 149.77 | G11: 149.422 | H11: 1 | I11: 0.4 | J11: 1.79 | K11: Win | L11: 17.4 | M11: =M10+L11 -> 179.5 | N11: =MAX($M$2:M11) -> 179.5 | O11: =N11-M11 -> 0
A12: 11 | B12: 2026-03-17 | C12: EUR/USD | D12: SELL | E12: 1.08498 | F12: 1.08724 | G12: 1.0782 | H12: 3 | I12: 0.94 | J12: 2.88 | K12: Loss | L12: -22.6 | M12: =M11+L12 -> 156.9 | N12: =MAX($M$2:M12) -> 179.5 | O12: =N12-M12 -> 22.6
A13: 12 | B13: 2026-03-18 | C13: EUR/USD | D13: BUY | E13: 1.07666 | F13: 1.07462 | G13: 1.0787 | H13: 1 | I13: 0.44 | J13: 1.89 | K13: Loss | L13: -20.4 | M13: =M12+L13 -> 136.5 | N13: =MAX($M$2:M13) -> 179.5 | O13: =N13-M13 -> 43
A14: 13 | B14: 2026-03-19 | C14: EUR/USD | D14: BUY | E14: 1.0835 | F14: 1.08176 | G14: 1.08698 | H14: 2 | I14: 0.73 | J14: 2.46 | K14: Win | L14: 34.8 | M14: =M13+L14 -> 171.3 | N14: =MAX($M$2:M14) -> 179.5 | O14: =N14-M14 -> 8.2
... A38: 37 | B38: 2026-04-28 | C38: EUR/USD | D38: SELL | E38: 1.08167 | F38: 1.08334 | G38: 1.07833 | H38: 2 | I38: 0.82 | J38: 2.64 | K38: Win | L38: 33.4 | M38: =M37+L38 -> 493 | N38: =MAX($M$2:M38) -> 493 | O38: =N38-M38 -> 0

Sheet Historical_Data
A1: Bar | B1: Date | C1: Time | D1: Session | E1: Open | F1: High | G1: Low | H1: Close | I1: Body | J1: Range | K1: Efficiency | L1: TrueRange | M1: ATR14 | N1: EMA21 | O1: AvgBody14 | P1: RecentRange5 | Q1: PriorRange5 | R1: RegimeRatio
A2: 1 | B2: 2026-03-02 | C2: 01:00 | D2: London | E2: 1.085 | F2: 1.08518 | G2: 1.08484 | H2: 1.085 | I2: =ABS(H2-E2) -> 0 | J2: =F2-G2 -> 0.00034 | K2: =IF(J2=0,0,I2/J2) -> 0 | L2: =F2-G2 -> 0.00034 | M2: =AVERAGE(L2:L2) -> 0.00034 | N2: =H2 -> 1.085 | O2: =AVERAGE(I2:I2) -> 0 | P2: =AVERAGE(J2:J2) -> 0.00034 | Q2: =AVERAGE(J2:J2) -> 0.00034 | R2: =IF(Q2=0,0,P2/Q2) -> 1
A3: 2 | B3: 2026-03-02 | C3: 02:00 | D3: London | E3: 1.085 | F3: 1.08527 | G3: 1.08343 | H3: 1.08402 | I3: =ABS(H3-E3) -> 0.00098 | J3: =F3-G3 -> 0.00184 | K3: =IF(J3=0,0,I3/J3) -> 0.5326087 | L3: =MAX(F3-G3,ABS(F3-H2),ABS(G3-H2)) -> 0.00184 | M3: =AVERAGE(L2:L3) -> 0.00109 | N3: =H3*0.0909090909090909+N2*(1-0.0909090909090909) -> 1.0849109 | O3: =AVERAGE(I2:I3) -> 0.00049 | P3: =AVERAGE(J2:J3) -> 0.00109 | Q3: =AVERAGE(J2:J2) -> 0.00034 | R3: =IF(Q3=0,0,P3/Q3) -> 3.2058824
A4: 3 | B4: 2026-03-02 | C4: 03:00 | D4: London | E4: 1.08402 | F4: 1.08489 | G4: 1.08373 | H4: 1.08409 | I4: =ABS(H4-E4) -> 7e-05 | J4: =F4-G4 -> 0.00116 | K4: =IF(J4=0,0,I4/J4) -> 0.060344828 | L4: =MAX(F4-G4,ABS(F4-H3),ABS(G4-H3)) -> 0.00116 | M4: =AVERAGE(L2:L4) -> 0.0011133333 | N4: =H4*0.0909090909090909+N3*(1-0.0909090909090909) -> 1.0848363 | O4: =AVERAGE(I2:I4) -> 0.00035 | P4: =AVERAGE(J2:J4) -> 0.0011133333 | Q4: =AVERAGE(J2:J2) -> 0.00034 | R4: =IF(Q4=0,0,P4/Q4) -> 3.2745098
A5: 4 | B5: 2026-03-02 | C5: 04:00 | D5: London | E5: 1.08409 | F5: 1.08438 | G5: 1.08319 | H5: 1.08341 | I5: =ABS(H5-E5) -> 0.00068 | J5: =F5-G5 -> 0.00119 | K5: =IF(J5=0,0,I5/J5) -> 0.57142857 | L5: =MAX(F5-G5,ABS(F5-H4),ABS(G5-H4)) -> 0.00119 | M5: =AVERAGE(L2:L5) -> 0.0011325 | N5: =H5*0.0909090909090909+N4*(1-0.0909090909090909) -> 1.0847066 | O5: =AVERAGE(I2:I5) -> 0.0004325 | P5: =AVERAGE(J2:J5) -> 0.0011325 | Q5: =AVERAGE(J2:J2) -> 0.00034 | R5: =IF(Q5=0,0,P5/Q5) -> 3.3308824
A6: 5 | B6: 2026-03-02 | C6: 05:00 | D6: London | E6: 1.08341 | F6: 1.08408 | G6: 1.08339 | H6: 1.08352 | I6: =ABS(H6-E6) -> 0.00011 | J6: =F6-G6 -> 0.00069 | K6: =IF(J6=0,0,I6/J6) -> 0.15942029 | L6: =MAX(F6-G6,ABS(F6-H5),ABS(G6-H5)) -> 0.00069 | M6: =AVERAGE(L2:L6) -> 0.001044 | N6: =H6*0.0909090909090909+N5*(1-0.0909090909090909) -> 1.0845987 | O6: =AVERAGE(I2:I6) -> 0.000368 | P6: =AVERAGE(J2:J6) -> 0.001044 | Q6: =AVERAGE(J2:J2) -> 0.00034 | R6: =IF(Q6=0,0,P6/Q6) -> 3.0705882
A7: 6 | B7: 2026-03-02 | C7: 06:00 | D7: Off-session | E7: 1.08352 | F7: 1.08509 | G7: 1.08325 | H7: 1.08429 | I7: =ABS(H7-E7) -> 0.00077 | J7: =F7-G7 -> 0.00184 | K7: =IF(J7=0,0,I7/J7) -> 0.41847826 | L7: =MAX(F7-G7,ABS(F7-H6),ABS(G7-H6)) -> 0.00184 | M7: =AVERAGE(L2:L7) -> 0.0011766667 | N7: =H7*0.0909090909090909+N6*(1-0.0909090909090909) -> 1.0845707 | O7: =AVERAGE(I2:I7) -> 0.000435 | P7: =AVERAGE(J3:J7) -> 0.001344 | Q7: =AVERAGE(J2:J2) -> 0.00034 | R7: =IF(Q7=0,0,P7/Q7) -> 3.9529412
A8: 7 | B8: 2026-03-02 | C8: 07:00 | D8: Off-session | E8: 1.08429 | F8: 1.08506 | G8: 1.08109 | H8: 1.08219 | I8: =ABS(H8-E8) -> 0.0021 | J8: =F8-G8 -> 0.00397 | K8: =IF(J8=0,0,I8/J8) -> 0.52896725 | L8: =MAX(F8-G8,ABS(F8-H7),ABS(G8-H7)) -> 0.00397 | M8: =AVERAGE(L2:L8) -> 0.0015757143 | N8: =H8*0.0909090909090909+N7*(1-0.0909090909090909) -> 1.0843543 | O8: =AVERAGE(I2:I8) -> 0.00067285714 | P8: =AVERAGE(J4:J8) -> 0.00177 | Q8: =AVERAGE(J2:J3) -> 0.00109 | R8: =IF(Q8=0,0,P8/Q8) -> 1.6238532
A9: 8 | B9: 2026-03-02 | C9: 08:00 | D9: New York | E9: 1.08219 | F9: 1.08296 | G9: 1.08177 | H9: 1.08194 | I9: =ABS(H9-E9) -> 0.00025 | J9: =F9-G9 -> 0.00119 | K9: =IF(J9=0,0,I9/J9) -> 0.21008403 | L9: =MAX(F9-G9,ABS(F9-H8),ABS(G9-H8)) -> 0.00119 | M9: =AVERAGE(L2:L9) -> 0.0015275 | N9: =H9*0.0909090909090909+N8*(1-0.0909090909090909) -> 1.0841348 | O9: =AVERAGE(I2:I9) -> 0.00062 | P9: =AVERAGE(J5:J9) -> 0.001776 | Q9: =AVERAGE(J2:J4) -> 0.0011133333 | R9: =IF(Q9=0,0,P9/Q9) -> 1.5952096
A10: 9 | B10: 2026-03-02 | C10: 09:00 | D10: New York | E10: 1.08194 | F10: 1.08222 | G10: 1.08043 | H10: 1.08211 | I10: =ABS(H10-E10) -> 0.00017 | J10: =F10-G10 -> 0.00179 | K10: =IF(J10=0,0,I10/J10) -> 0.094972067 | L10: =MAX(F10-G10,ABS(F10-H9),ABS(G10-H9)) -> 0.00179 | M10: =AVERAGE(L2:L10) -> 0.0015566667 | N10: =H10*0.0909090909090909+N9*(1-0.0909090909090909) -> 1.0839507 | O10: =AVERAGE(I2:I10) -> 0.00057 | P10: =AVERAGE(J6:J10) -> 0.001896 | Q10: =AVERAGE(J2:J5) -> 0.0011325 | R10: =IF(Q10=0,0,P10/Q10) -> 1.6741722
A11: 10 | B11: 2026-03-02 | C11: 10:00 | D11: New York | E11: 1.08211 | F11: 1.08214 | G11: 1.08145 | H11: 1.08152 | I11: =ABS(H11-E11) -> 0.00059 | J11: =F11-G11 -> 0.00069 | K11: =IF(J11=0,0,I11/J11) -> 0.85507246 | L11: =MAX(F11-G11,ABS(F11-H10),ABS(G11-H10)) -> 0.00069 | M11: =AVERAGE(L2:L11) -> 0.00147 | N11: =H11*0.0909090909090909+N10*(1-0.0909090909090909) -> 1.0837297 | O11: =AVERAGE(I2:I11) -> 0.000572 | P11: =AVERAGE(J7:J11) -> 0.001896 | Q11: =AVERAGE(J2:J6) -> 0.001044 | R11: =IF(Q11=0,0,P11/Q11) -> 1.816092
A12: 11 | B12: 2026-03-02 | C12: 11:00 | D12: New York | E12: 1.08152 | F12: 1.0818 | G12: 1.07925 | H12: 1.07983 | I12: =ABS(H12-E12) -> 0.00169 | J12: =F12-G12 -> 0.00255 | K12: =IF(J12=0,0,I12/J12) -> 0.6627451 | L12: =MAX(F12-G12,ABS(F12-H11),ABS(G12-H11)) -> 0.00255 | M12: =AVERAGE(L2:L12) -> 0.0015681818 | N12: =H12*0.0909090909090909+N11*(1-0.0909090909090909) -> 1.0833752 | O12: =AVERAGE(I2:I12) -> 0.00067363636 | P12: =AVERAGE(J8:J12) -> 0.002038 | Q12: =AVERAGE(J3:J7) -> 0.001344 | R12: =IF(Q12=0,0,P12/Q12) -> 1.516369
A13: 12 | B13: 2026-03-02 | C13: 12:00 | D13: New York | E13: 1.07983 | F13: 1.08047 | G13: 1.07846 | H13: 1.07894 | I13: =ABS(H13-E13) -> 0.00089 | J13: =F13-G13 -> 0.00201 | K13: =IF(J13=0,0,I13/J13) -> 0.44278607 | L13: =MAX(F13-G13,ABS(F13-H12),ABS(G13-H12)) -> 0.00201 | M13: =AVERAGE(L2:L13) -> 0.001605 | N13: =H13*0.0909090909090909+N12*(1-0.0909090909090909) -> 1.082972 | O13: =AVERAGE(I2:I13) -> 0.00069166667 | P13: =AVERAGE(J9:J13) -> 0.001646 | Q13: =AVERAGE(J4:J8) -> 0.00177 | R13: =IF(Q13=0,0,P13/Q13) -> 0.9299435
A14: 13 | B14: 2026-03-02 | C14: 13:00 | D14: Off-session | E14: 1.07894 | F14: 1.07947 | G14: 1.07856 | H14: 1.07891 | I14: =ABS(H14-E14) -> 3e-05 | J14: =F14-G14 -> 0.00091 | K14: =IF(J14=0,0,I14/J14) -> 0.032967033 | L14: =MAX(F14-G14,ABS(F14-H13),ABS(G14-H13)) -> 0.00091 | M14: =AVERAGE(L2:L14) -> 0.0015515385 | N14: =H14*0.0909090909090909+N13*(1-0.0909090909090909) -> 1.0826027 | O14: =AVERAGE(I2:I14) -> 0.00064076923 | P14: =AVERAGE(J10:J14) -> 0.00159 | Q14: =AVERAGE(J5:J9) -> 0.001776 | R14: =IF(Q14=0,0,P14/Q14) -> 0.89527027
A15: 14 | B15: 2026-03-03 | C15: 01:00 | D15: London | E15: 1.07891 | F15: 1.07897 | G15: 1.07875 | H15: 1.07878 | I15: =ABS(H15-E15) -> 0.00013 | J15: =F15-G15 -> 0.00022 | K15: =IF(J15=0,0,I15/J15) -> 0.59090909 | L15: =MAX(F15-G15,ABS(F15-H14),ABS(G15-H14)) -> 0.00022 | M15: =AVERAGE(L2:L15) -> 0.0014564286 | N15: =H15*0.0909090909090909+N14*(1-0.0909090909090909) -> 1.0822552 | O15: =AVERAGE(I2:I15) -> 0.00060428571 | P15: =AVERAGE(J11:J15) -> 0.001276 | Q15: =AVERAGE(J6:J10) -> 0.001896 | R15: =IF(Q15=0,0,P15/Q15) -> 0.67299578
A16: 15 | B16: 2026-03-03 | C16: 02:00 | D16: London | E16: 1.07878 | F16: 1.07883 | G16: 1.07662 | H16: 1.07744 | I16: =ABS(H16-E16) -> 0.00134 | J16: =F16-G16 -> 0.00221 | K16: =IF(J16=0,0,I16/J16) -> 0.60633484 | L16: =MAX(F16-G16,ABS(F16-H15),ABS(G16-H15)) -> 0.00221 | M16: =AVERAGE(L3:L16) -> 0.00159 | N16: =H16*0.0909090909090909+N15*(1-0.0909090909090909) -> 1.0818175 | O16: =AVERAGE(I3:I16) -> 0.0007 | P16: =AVERAGE(J12:J16) -> 0.00158 | Q16: =AVERAGE(J7:J11) -> 0.001896 | R16: =IF(Q16=0,0,P16/Q16) -> 0.83333333
A17: 16 | B17: 2026-03-03 | C17: 03:00 | D17: London | E17: 1.07744 | F17: 1.07795 | G17: 1.07566 | H17: 1.07574 | I17: =ABS(H17-E17) -> 0.0017 | J17: =F17-G17 -> 0.00229 | K17: =IF(J17=0,0,I17/J17) -> 0.74235808 | L17: =MAX(F17-G17,ABS(F17-H16),ABS(G17-H16)) -> 0.00229 | M17: =AVERAGE(L4:L17) -> 0.0016221429 | N17: =H17*0.0909090909090909+N16*(1-0.0909090909090909) -> 1.081265 | O17: =AVERAGE(I4:I17) -> 0.00075142857 | P17: =AVERAGE(J13:J17) -> 0.001528 | Q17: =AVERAGE(J8:J12) -> 0.002038 | R17: =IF(Q17=0,0,P17/Q17) -> 0.74975466
A18: 17 | B18: 2026-03-03 | C18: 04:00 | D18: London | E18: 1.07574 | F18: 1.07694 | G18: 1.07457 | H18: 1.07503 | I18: =ABS(H18-E18) -> 0.00071 | J18: =F18-G18 -> 0.00237 | K18: =IF(J18=0,0,I18/J18) -> 0.29957806 | L18: =MAX(F18-G18,ABS(F18-H17),ABS(G18-H17)) -> 0.00237 | M18: =AVERAGE(L5:L18) -> 0.0017085714 | N18: =H18*0.0909090909090909+N17*(1-0.0909090909090909) -> 1.0806982 | O18: =AVERAGE(I5:I18) -> 0.00079714286 | P18: =AVERAGE(J14:J18) -> 0.0016 | Q18: =AVERAGE(J9:J13) -> 0.001646 | R18: =IF(Q18=0,0,P18/Q18) -> 0.97205346
A19: 18 | B19: 2026-03-03 | C19: 05:00 | D19: London | E19: 1.07503 | F19: 1.07507 | G19: 1.07336 | H19: 1.07371 | I19: =ABS(H19-E19) -> 0.00132 | J19: =F19-G19 -> 0.00171 | K19: =IF(J19=0,0,I19/J19) -> 0.77192982 | L19: =MAX(F19-G19,ABS(F19-H18),ABS(G19-H18)) -> 0.00171 | M19: =AVERAGE(L6:L19) -> 0.0017457143 | N19: =H19*0.0909090909090909+N18*(1-0.0909090909090909) -> 1.0800629 | O19: =AVERAGE(I6:I19) -> 0.00084285714 | P19: =AVERAGE(J15:J19) -> 0.00176 | Q19: =AVERAGE(J10:J14) -> 0.00159 | R19: =IF(Q19=0,0,P19/Q19) -> 1.1069182
A20: 19 | B20: 2026-03-03 | C20: 06:00 | D20: Off-session | E20: 1.07371 | F20: 1.07412 | G20: 1.07346 | H20: 1.0735 | I20: =ABS(H20-E20) -> 0.00021 | J20: =F20-G20 -> 0.00066 | K20: =IF(J20=0,0,I20/J20) -> 0.31818182 | L20: =MAX(F20-G20,ABS(F20-H19),ABS(G20-H19)) -> 0.00066 | M20: =AVERAGE(L7:L20) -> 0.0017435714 | N20: =H20*0.0909090909090909+N19*(1-0.0909090909090909) -> 1.0794662 | O20: =AVERAGE(I7:I20) -> 0.00085 | P20: =AVERAGE(J16:J20) -> 0.001848 | Q20: =AVERAGE(J11:J15) -> 0.001276 | R20: =IF(Q20=0,0,P20/Q20) -> 1.4482759
A21: 20 | B21: 2026-03-03 | C21: 07:00 | D21: Off-session | E21: 1.0735 | F21: 1.0751 | G21: 1.0731 | H21: 1.07424 | I21: =ABS(H21-E21) -> 0.00074 | J21: =F21-G21 -> 0.002 | K21: =IF(J21=0,0,I21/J21) -> 0.37 | L21: =MAX(F21-G21,ABS(F21-H20),ABS(G21-H20)) -> 0.002 | M21: =AVERAGE(L8:L21) -> 0.001755 | N21: =H21*0.0909090909090909+N20*(1-0.0909090909090909) -> 1.0789911 | O21: =AVERAGE(I8:I21) -> 0.00084785714 | P21: =AVERAGE(J17:J21) -> 0.001806 | Q21: =AVERAGE(J12:J16) -> 0.00158 | R21: =IF(Q21=0,0,P21/Q21) -> 1.143038
A22: 21 | B22: 2026-03-03 | C22: 08:00 | D22: New York | E22: 1.07424 | F22: 1.07474 | G22: 1.07416 | H22: 1.07446 | I22: =ABS(H22-E22) -> 0.00022 | J22: =F22-G22 -> 0.00058 | K22: =IF(J22=0,0,I22/J22) -> 0.37931034 | L22: =MAX(F22-G22,ABS(F22-H21),ABS(G22-H21)) -> 0.00058 | M22: =AVERAGE(L9:L22) -> 0.0015128571 | N22: =H22*0.0909090909090909+N21*(1-0.0909090909090909) -> 1.0785792 | O22: =AVERAGE(I9:I22) -> 0.00071357143 | P22: =AVERAGE(J18:J22) -> 0.001464 | Q22: =AVERAGE(J13:J17) -> 0.001528 | R22: =IF(Q22=0,0,P22/Q22) -> 0.95811518
A23: 22 | B23: 2026-03-03 | C23: 09:00 | D23: New York | E23: 1.07446 | F23: 1.07481 | G23: 1.07304 | H23: 1.07315 | I23: =ABS(H23-E23) -> 0.00131 | J23: =F23-G23 -> 0.00177 | K23: =IF(J23=0,0,I23/J23) -> 0.74011299 | L23: =MAX(F23-G23,ABS(F23-H22),ABS(G23-H22)) -> 0.00177 | M23: =AVERAGE(L10:L23) -> 0.0015542857 | N23: =H23*0.0909090909090909+N22*(1-0.0909090909090909) -> 1.0780856 | O23: =AVERAGE(I10:I23) -> 0.00078928571 | P23: =AVERAGE(J19:J23) -> 0.001344 | Q23: =AVERAGE(J14:J18) -> 0.0016 | R23: =IF(Q23=0,0,P23/Q23) -> 0.84
A24: 23 | B24: 2026-03-03 | C24: 10:00 | D24: New York | E24: 1.07315 | F24: 1.07483 | G24: 1.07236 | H24: 1.07414 | I24: =ABS(H24-E24) -> 0.00099 | J24: =F24-G24 -> 0.00247 | K24: =IF(J24=0,0,I24/J24) -> 0.40080972 | L24: =MAX(F24-G24,ABS(F24-H23),ABS(G24-H23)) -> 0.00247 | M24: =AVERAGE(L11:L24) -> 0.0016028571 | N24: =H24*0.0909090909090909+N23*(1-0.0909090909090909) -> 1.077727 | O24: =AVERAGE(I11:I24) -> 0.00084785714 | P24: =AVERAGE(J20:J24) -> 0.001496 | Q24: =AVERAGE(J15:J19) -> 0.00176 | R24: =IF(Q24=0,0,P24/Q24) -> 0.85
A25: 24 | B25: 2026-03-03 | C25: 11:00 | D25: New York | E25: 1.07414 | F25: 1.07453 | G25: 1.07207 | H25: 1.07327 | I25: =ABS(H25-E25) -> 0.00087 | J25: =F25-G25 -> 0.00246 | K25: =IF(J25=0,0,I25/J25) -> 0.35365854 | L25: =MAX(F25-G25,ABS(F25-H24),ABS(G25-H24)) -> 0.00246 | M25: =AVERAGE(L12:L25) -> 0.0017292857 | N25: =H25*0.0909090909090909+N24*(1-0.0909090909090909) -> 1.0773218 | O25: =AVERAGE(I12:I25) -> 0.00086785714 | P25: =AVERAGE(J21:J25) -> 0.001856 | Q25: =AVERAGE(J16:J20) -> 0.001848 | R25: =IF(Q25=0,0,P25/Q25) -> 1.004329
A26: 25 | B26: 2026-03-03 | C26: 12:00 | D26: New York | E26: 1.07327 | F26: 1.07333 | G26: 1.072 | H26: 1.07276 | I26: =ABS(H26-E26) -> 0.00051 | J26: =F26-G26 -> 0.00133 | K26: =IF(J26=0,0,I26/J26) -> 0.38345865 | L26: =MAX(F26-G26,ABS(F26-H25),ABS(G26-H25)) -> 0.00133 | M26: =AVERAGE(L13:L26) -> 0.0016421429 | N26: =H26*0.0909090909090909+N25*(1-0.0909090909090909) -> 1.0769071 | O26: =AVERAGE(I13:I26) -> 0.00078357143 | P26: =AVERAGE(J22:J26) -> 0.001722 | Q26: =AVERAGE(J17:J21) -> 0.001806 | R26: =IF(Q26=0,0,P26/Q26) -> 0.95348837
... A151: 150 | B151: 2026-03-13 | C151: 07:00 | D151: Off-session | E151: 1.05698 | F151: 1.05743 | G151: 1.05638 | H151: 1.05673 | I151: =ABS(H151-E151) -> 0.00025 | J151: =F151-G151 -> 0.00105 | K151: =IF(J151=0,0,I151/J151) -> 0.23809524 | L151: =MAX(F151-G151,ABS(F151-H150),ABS(G151-H150)) -> 0.00105 | M151: =AVERAGE(L138:L151) -> 0.0018064286 | N151: =H151*0.0909090909090909+N150*(1-0.0909090909090909) -> 1.0591571 | O151: =AVERAGE(I138:I151) -> 0.00077214286 | P151: =AVERAGE(J147:J151) -> 0.00187 | Q151: =AVERAGE(J142:J146) -> 0.001548 | R151: =IF(Q151=0,0,P151/Q151) -> 1.2080103
